{"url": "http://www.synverse.com/index.php?page=synverse-webcore-framework", "timestamp": 1258433051, "tags": ["webcore", "framework", "frameworks"]}
{"url": "http://www.getzephyr.com/company/zephyr_partners.php", "timestamp": 1258433045, "tags": ["synverse", "partners", "zephyr"]}
{"url": "http://www.mozilla.com/en-GB/firefox/help/", "timestamp": 1258501604, "tags": ["mozilla", "firefox"]}
{"url": "http://www.synverse.com/index.php?page=working-synverse", "timestamp": 1258433060, "tags": ["careers", "working", "synverse"]}
{"url": "http://www.siliconindia.com/blogs/siuserblog.php?vHTFuQ7ZWSHnFY4FxiU2C61yqctoS16h+eVrApux3+", "timestamp": 1258433044, "tags": ["iso", "9001", "certification"]}
{"url": "http://www.synverse.com/index.php?page=newsletter", "timestamp": 1258433044, "tags": ["launched", "customer", "mvnos", "telco", "portal", "innovative", "services", "newsletter", "2009"]}
{"url": "http://eshop.talash.com/shop/category/apparels_&_accessories/", "timestamp": 1258420933, "tags": ["mens", "womens", "apparel", "accessories", "clothing"]}
{"url": "http://www.2circles.com/", "timestamp": 1258432735, "tags": ["circles", "communications", "cheap", "international", "0870", "0845", "telephones"]}
{"url": "http://www.thebog.webs.com/", "timestamp": 1258481122, "tags": ["fun", "social", "chat", "forum", "games"]}
{"url": "http://fivestarhotelresort.blog.co.in/2009/11/16/tips-for-international-travel-make-tour-is-fun-and-exciting/", "timestamp": 1258423153, "tags": ["business", "india"]}
{"url": "http://bagbunch.com/bizarre-purses-handbags/", "timestamp": 1258443729, "tags": ["bags", "bizarre", "crazy", "odd", "strange", "unique", "unusual", "weird"]}
{"url": "http://watchlawabidingcitizenfullmovie.weebly.com/", "timestamp": 1258450586, "tags": ["download", "law", "abiding", "citizen"]}
{"url": "http://libraryden.com/", "timestamp": 1258456400, "tags": ["catalog", "books", "online"]}
{"url": "http://www.seenation.com/view_full_news_details.php?newsid=116276&title=Synverse%20Expanding%20India%20Operations", "timestamp": 1258433041, "tags": ["product", "engineering", "services", "design"]}
{"url": "http://www.joshuabell.com/user/ittrainingcourse", "timestamp": 1258423796, "tags": ["online", "courses", "training", "certifications", "certification"]}
{"url": "http://hubpages.com/hub/How-To-Increase-Myspace-Mp3-Plays", "timestamp": 1258440008, "tags": ["myspace", "play", "increaser", "hellofriendz"]}
{"url": "http://www.krystal-limousines.co.uk/", "timestamp": 1258456362, "tags": ["limo", "lincoln", "hire", "engine", "krystal", "limousine"]}
{"url": "http://www.rajasthantoursonline.com/tours/forts-palace-tour.htm", "timestamp": 1258419929, "tags": ["rajasthan", "palaces", "tours", "forts", "tour"]}
{"url": "http://www.uxsight.com/category/31746/christmas-gifts.html", "timestamp": 1258424615, "tags": ["christmas", "gifts", "xmas", "presents"]}
{"url": "http://www.themoccasinshop.com/", "timestamp": 1258456432, "tags": ["moccasins"]}
{"url": "http://www.offshoreaccountingtaxation.com/", "timestamp": 1258501334, "tags": ["outsourcing", "services"]}
{"url": "http://huequang.vn/Product/1/Gach-Khong-Nung.html", "timestamp": 1258424310, "tags": ["gach", "khong", "nung", "gom", "su", "dat", "hoa", "da"]}
{"url": "http://www.handloommark.gov.in/", "timestamp": 1258441593, "tags": ["handloom", "mark", "-", "industry", "fabrics", "production", "hand", "woven", "products", "retail", "outlets", "sector", "powerloom"]}
{"url": "http://www.free-press-release.com/news/200906/1245416275.html", "timestamp": 1258433045, "tags": ["iso", "9001", "2000", "2008", "9001:2000", "9001:2008", "certification", "training", "standard"]}
{"url": "http://www.arb-bearings.com/", "timestamp": 1258438421, "tags": ["bearing", "manufacturer", "india", "exporter", "bearings", "tappered", "roller", "ball", "distributors", "products", "importer", "wholesale", "supplier", "dealer", "distributor"]}
{"url": "http://www.synverse.com/index.php?page=customers", "timestamp": 1258433063, "tags": ["industry", "domain", "telco", "telecommunication", "telecoms", "health", "banking", "retail", "life", "sciences", "finance", "tibco", "bea"]}
{"url": "http://fivestarhotelresort.blog.co.in/2009/11/16/tips-for-international-travel-make-tour-is-fun-and-exciting/", "timestamp": 1258423152, "tags": ["international", "tour", "tips", "travel", "star", "hotel", "resort", "online", "tourism"]}
{"url": "http://www.prlog.org/10262248-synverse-attains-iso-9001-certification.html", "timestamp": 1258433045, "tags": ["iso", "9001", "standard", "iso9001", "quality", "management", "audit", "certification", "safety", "assurance"]}
{"url": "http://ameliapt.blogspot.com/2009/11/hafizah-sinetron-md-entertainment.html", "timestamp": 1258460029, "tags": ["sinetron"]}
{"url": "http://www.onlineprnews.com/news/2509-1245829768-synverse-attains-iso-9001-certification.html", "timestamp": 1258433044, "tags": ["attains", "iso", "9001", "certification"]}
{"url": "http://www.friesland-kleinanzeiger.de/", "timestamp": 1258454431, "tags": ["kleinanzeigen"]}
{"url": "http://www.essaycapital.com/blog/all-about-essay/admesy/886", "timestamp": 1258433312, "tags": ["essay", "personal", "interesting"]}
{"url": "http://www.costaricaviews.com/category/costa-rica-beach-front/", "timestamp": 1258418423, "tags": ["costa", "rica", "beach", "beaches"]}
{"url": "http://www.2circles.com/", "timestamp": 1258432734, "tags": ["business", "telecommunications", "phones", "phone", "lines", "mobiles", "2"]}
{"url": "http://huequang.vn/DetailBody/15/Cong-nghe-%E2%80%9CDat-hoa-da%E2%80%9D-trong-san-xuat-gach-khong-nung.html", "timestamp": 1258424343, "tags": ["dat", "hoa", "da"]}
{"url": "http://www.mountorama.com/", "timestamp": 1258430234, "tags": ["tv", "wall", "mounts", "lcd", "mount", "plasma"]}
{"url": "http://www.essaycapital.com/blog/all-about-essay/ccrrp/915", "timestamp": 1258433663, "tags": ["cancer", "topic", "topics"]}
{"url": "http://www.onlineprnews.com/news/4155-1249640383-synverse-expanding-india-operations.html", "timestamp": 1258433041, "tags": ["golabal", "offshore", "outsourcing", "software", "development", "global", "sourcing", "custom", "business", "process", "services"]}
{"url": "http://www.synverse.com/index.php?page=innovation", "timestamp": 1258433067, "tags": ["enterprise", "web", "2.0", "saas", "cloud", "computing", "green", "virtualisation", "mobility"]}
{"url": "http://www.commsbusiness.co.uk/News_Article_JS1.cfm?NewsID=8648", "timestamp": 1258433042, "tags": ["telecoms", "comms", "business", "news", "telecommunications", "jobs", "communications", "dealer", "magazine", "publication", "resellers", "voip", "latest", "convergence", "summit"]}
{"url": "http://www.goarticles.com/cgi-bin/showa.cgi?C=2219583", "timestamp": 1258430527, "tags": ["sardinia", "villas", "collection"]}
{"url": "http://www.synverse.com/index.php?page=about-us", "timestamp": 1258433063, "tags": ["health", "banking", "retail", "life", "sciences", "finance", "technology"]}
{"url": "http://www.essaycapital.com/blog/all-about-essay/ccrrp/915", "timestamp": 1258433664, "tags": ["research", "paper", "qualitative", "guidelines"]}
{"url": "http://eshop.talash.com/shop/category/gift_certificates/", "timestamp": 1258421004, "tags": ["gift", "certificates", "vouchers", "food", "grand", "bhagvati", "dominos", "sodexo"]}
{"url": "http://www.synverse.com/index.php?page=industries", "timestamp": 1258433068, "tags": ["telco", "telecommunication", "telecoms", "health", "banking", "retail", "life", "sciences", "finance"]}
{"url": "http://www.internetdatingservices.com.au/blogs/singles-dating-sites-to-meet-a-mate", "timestamp": 1258429635, "tags": ["dating", "sites", "singles", "personals", "date", "relationship", "free", "online", "internet", "hot", "women", "casual"]}
{"url": "http://www.tibco.co.uk/company/news/releases/2009/press957.jsp", "timestamp": 1258433053, "tags": ["soa", "governance", "magic", "quadrant", "leaders", "implementations"]}
{"url": "http://www.phoenixpdx.com/", "timestamp": 1258456529, "tags": ["electrician", "portland"]}
{"url": "http://gci.edu/", "timestamp": 1258454568, "tags": ["beauty", "school", "conyers", "ga", "cosmetology", "massage", "therapy"]}
{"url": "http://www.gateway2morocco.com/tours_discover_morocco.html", "timestamp": 1258501280, "tags": ["morocco", "adventure", "tours", "private"]}
{"url": "http://www.synverse.com/index.php?page=customers", "timestamp": 1258433064, "tags": ["mq", "oracle", "sap", "chordiant", "seibel", "php", "java", "joomla", "j2ee", ".net", "cake", "consulting", "bpo", "crm", "eai", "testing", "quality", "assurance"]}
{"url": "http://www.xing.com/app/forum?op=showarticles;id=19621510", "timestamp": 1258433044, "tags": ["introducing", "synverse", "global", "services", "support", "telecoms", "software", "companies", "crm", "tibco", "soa", "eai", "erp", "michael.knuckey"]}
{"url": "http://www.photo-to-dvd.com/tutorial/widescreen-youtube-video.html#150", "timestamp": 1258496343, "tags": ["youtube", "widescreen", "16:9", "video"]}
{"url": "http://cibol.net/", "timestamp": 1258501305, "tags": ["internet", "marketing", "software", "domain", "hosting"]}
{"url": "http://blog.spinxwebdesign.com/article/a-blog-is-more-seo-friendly-compared-to-a-website/", "timestamp": 1258465137, "tags": ["web", "design", "los", "angeles", "website", "company"]}
{"url": "http://www.pressreleasepoint.com/synverse-and-gateway-technolabs-partner-provide-end2end-implementation-and-managed-services", "timestamp": 1258433038, "tags": ["synverse", "gateway", "technolabs", "saas", "managed", "services"]}
{"url": "http://www.synverse.com/index.php?page=methodology", "timestamp": 1258433066, "tags": ["synverse", "methodology", "implementation", "business", "process", "delivery", "sim", "project", "management"]}
{"url": "http://www.associatedcontent.com/article/2398454/study_finds_bisexuality_in_women_not.html?cat=41", "timestamp": 1258499216, "tags": ["bisexuality", "women", "sexual", "identity", "behavior", "attraction", "relationships", "orientation", "dating", "monogamy"]}
{"url": "http://www.telecommentor.com/jobs/job/2688/telecom-testers-at-synverse/", "timestamp": 1258433054, "tags": ["apis", "shell", "scripting", "strong", "solaris", "10", "telecom", "testers"]}
{"url": "http://www.luqman-technologies.com/", "timestamp": 1258418294, "tags": ["web", "design", "development", "programming", "search", "engine", "optimization", "marketing", "internet", "seo"]}
{"url": "http://www.governorsclubinc.com/role-of-health-care-reporting-systems-in-hospital/", "timestamp": 1258428546, "tags": ["health", "medicine", "treatment"]}
{"url": "http://www.synverse.com/index.php?page=privacy-statement", "timestamp": 1258433058, "tags": ["3g", "voip", "m-commerce", "self", "care", "retail", "point", "sale", "product", "catalogue", "oracle", "telecommunication", "solutions", "enterprise", "resource", "planning", "application", "integration", "information", "services", "outsourcing", "consulting", "offshoring", "generation", "bss", "oss", "methodology", "qa", "intellectual", "property"]}
{"url": "http://www.toyotsrus.com.au/", "timestamp": 1258428633, "tags": ["toyota", "auto", "parts", "hilux", "corolla", "car", "camry", "hiace", "landcruiser", "exhaust", "brakes"]}
{"url": "http://www.onlywire.com/", "timestamp": 1258433057, "tags": ["onlywire"]}
{"url": "http://www.synverse.com/index.php?page=jobs-synverse", "timestamp": 1258433060, "tags": ["jobs", "careers", "search", "career", "job", "vacancy", "vacancies", "opportunity", "opportunities", "uk", "india", "industry", "domain", "telco", "telecommunication", "telecoms", "health", "banking", "retail"]}
{"url": "http://huequang.vn/DetailBody/15/Cong-nghe-%E2%80%9CDat-hoa-da%E2%80%9D-trong-san-xuat-gach-khong-nung.html", "timestamp": 1258424342, "tags": ["gach", "khong", "nung", "gom", "su"]}
{"url": "http://www.lasersec.in/laser-sticker.shtml", "timestamp": 1258441336, "tags": ["laser", "sticker", "hologram", "manufacturer", "holographic", "labels", "anti", "counterfeit", "packaging"]}
{"url": "http://www.pressreleasepoint.com/synverse-managed-service-proposition-isv%E2%80%99s-reducing-operating-cost-50%E2%80%9D", "timestamp": 1258433047, "tags": ["investments", "today", "employed", "businesses"]}
{"url": "http://www.erollover.com/blog/DJIA-dow-jones-industrial-average/", "timestamp": 1258476862, "tags": ["dow", "jones", "dow-jones-industrial-average", "dow-30", "djia", "stock-index"]}
{"url": "http://www.newdesignworld.com/press/story/14589", "timestamp": 1258433049, "tags": ["synverse", "sap", "footprint"]}
{"url": "http://www.california-auto-accidents.com./", "timestamp": 1258443054, "tags": ["california", "auto", "accident", "sacramento", "attorneys", "personal", "injury", "medical", "malpractice", "death", "free", "case", "evaluation", "wrongful", "car", "accidents", "cell", "phone", "bicycle", "crashes", "automobile", "collisions", "premises", "liability", "product", "recalled"]}
{"url": "http://techrepublic.com.com/5208-10878-0.html?forumID=102&threadID=303796&start=0", "timestamp": 1258433047, "tags": ["anuj", "sachdeva", "executive", "management", "cio", "cto"]}
{"url": "http://www.synverse.com/index.php?page=moral-fibre", "timestamp": 1258433060, "tags": ["telco", "telecommunication", "telecoms", "health", "banking", "retail", "life", "sciences", "finance", "tibco", "bea", "mq", "oracle", "sap", "chordiant", "seibel", "php", "java", "joomla", "j2ee", ".net", "cake"]}
{"url": "http://cibol.net/", "timestamp": 1258501302, "tags": ["design"]}
{"url": "http://blog.fenon.com.br/artigos/dicas-de-como-fazer-uma-boa-redacao/", "timestamp": 1258448126, "tags": ["dicas", "boa", "redacao", "fazer"]}
{"url": "http://www.synverse.com/index.php?page=accelerators", "timestamp": 1258433064, "tags": ["synverse", "accelerators", "methodology"]}
{"url": "http://www.synverse.com/", "timestamp": 1258433070, "tags": ["tibco", "achievements", "products", "infrastructure", "management", "business", "intelligence"]}
{"url": "http://www.free-press-release.com/news/200908/1249902603.html", "timestamp": 1258433041, "tags": ["development", "outsourcing", "adm", "services", "offshore", "consulting"]}
{"url": "http://www.1888pressrelease.com/synverse-global-expertise-in-deployment-support-services-f-pr-158705.html", "timestamp": 1258433033, "tags": ["computing", "innovation", "frameworks", "accelerators", "methodolog"]}
{"url": "http://www.spiritvoyage.com/yogablog/index.php/2009/11/13/yoga-music-yogi-tea-a-way-to-entice-your-senses/", "timestamp": 1258417880, "tags": ["yoga", "music", "tea", "kundalini", "meditation"]}
{"url": "http://www.mozilla.com/en-GB/firefox/customize/", "timestamp": 1258501604, "tags": ["mozilla", "firefox"]}
{"url": "http://www.injury-attorneys.com/", "timestamp": 1258444601, "tags": ["auto", "accident", "california", "trucking", "motorcycle", "crash", "bicycle", "injuries", "drunk", "driver", "boating", "nursing", "abuse", "neglect", "negligent", "security", "wrongful", "death", "swimming", "pool/drowning", "slip", "fall", "dog", "bite", "attorney", "lawyer", "attorneys"]}
{"url": "http://www.photo-to-dvd.com/free-motion-menu-templates.html#150", "timestamp": 1258428308, "tags": ["dvd", "motion", "free", "templates", "menu"]}
{"url": "http://www.synverse.com/index.php?mact=News,cntnt01,detail,0&cntnt01articleid=6&cntnt01returnid=15", "timestamp": 1258433045, "tags": ["9001", "certification"]}
{"url": "http://pipes.yahoo.com/pipes/pipe.info?_id=iDpoiglX3hGVONNm0j6skA", "timestamp": 1258433046, "tags": ["pipes", "yahoo"]}
{"url": "http://www.pressreleasepoint.com/synverse-expanding-its-sap-footprint", "timestamp": 1258433049, "tags": ["sap", "solutions", "requirements", "businesses"]}
{"url": "http://www.seenation.com/view_full_news_details.php?newsid=124705&title=Synverse%20and%20Gateway%20Technolabs%20Partner%20to%20provide%20end2end%20Implementation%20and%20Managed%20Services", "timestamp": 1258433036, "tags": ["synverse", "gateway", "technolabs", "saas", "managed", "services", "cloud", "computing", "innovation", "frameworks", "accelerators", "methodologies", "solutions.", "offshore", "software", "outsourcing", "web"]}
{"url": "http://fivestarhotelresort.blogspot.com/2009/11/great-adventure-with-perfect-cruise.html", "timestamp": 1258423207, "tags": ["booking", "tour", "travel", "tourism", "business", "luxury", "vacation"]}
{"url": "http://www.synverse.com/index.php?page=accelerators", "timestamp": 1258433065, "tags": ["innovation", "frameworks", "business", "solution", "engine", "enablers", "global", "delivery", "model"]}
{"url": "http://www.erollover.com/education/investments/stock-options/stock-options-trading-101/", "timestamp": 1258476901, "tags": ["stock", "options", "trading", "option"]}
{"url": "http://www.synverse.com/index.php?page=industries", "timestamp": 1258433069, "tags": ["industry", "verticals", "consulting", "implementation", "end-to-end"]}
{"url": "http://cibol.net/", "timestamp": 1258501303, "tags": ["web", "development", "promotion"]}
{"url": "http://www.bookkeepingservicesindia.com/", "timestamp": 1258417643, "tags": ["bookkeeping", "services", "bank", "reconciliation", "statement", "general", "ledger", "accounting", "prepare"]}
{"url": "http://www.synverse.com/index.php?page=consulting", "timestamp": 1258433067, "tags": ["synverse"]}
{"url": "http://www.offgamers.com/world-of-warcraft/wow-us-c-16-2299.ogm", "timestamp": 1258416949, "tags": ["wow", "gold", "games"]}
{"url": "http://www.synverse.com/index.php?page=life-sciences-healthcare", "timestamp": 1258433064, "tags": ["synverse", "life", "science", "&", "healthcare", "practice", "services", "solutions"]}
{"url": "http://www.creativesanctuary.co.uk/", "timestamp": 1258438135, "tags": ["website", "designer", "uk", "designers", "custom", "web", "design", "ecommerce", "company", "services", "small", "business", "content", "management", "solution"]}
{"url": "http://sendgifts2india.com/shop/category/Gift_Certificates/", "timestamp": 1258421126, "tags": ["send", "gifts", "india", "gift", "certificates", "buy", "special", "vouchers", "certificate", "online", "like", "westside", "dominos", "pizza", "crossword", "shoppers", "stop"]}
{"url": "http://www.lyco.co.uk/Light-Fittings/Indoor-Light-Fittings/Bathroom-Lighting/Shaver-Lights/sc1437/p864.aspx", "timestamp": 1258445092, "tags": ["lights"]}
{"url": "http://www.handloommark.gov.in/", "timestamp": 1258441594, "tags": ["sectors"]}
{"url": "http://www.gateway2morocco.com/tours_discover_morocco.html", "timestamp": 1258501281, "tags": ["luxury", "cultural", "holiday", "vacation", "tour"]}
{"url": "http://www.barsisniega.com/high-paid-health-care-jobs/", "timestamp": 1258422624, "tags": ["health", "medicine", "treatment"]}
{"url": "http://www.essaycapital.com/blog/all-about-essay/abesy/896", "timestamp": 1258433485, "tags": ["autobiographical", "essay", "academic"]}
{"url": "http://www.essaycapital.com/blog/all-about-essay/argesy/890", "timestamp": 1258433347, "tags": ["argumentative", "essay", "writing", "essays", "academic", "projects", "assignments", "good"]}
{"url": "http://www.synverse.com/index.php?page=communication-media", "timestamp": 1258433064, "tags": ["synverse", "communication", "&", "media", "practice", "innovation", "telecommunication", "services", "solutions", "application", "network", "bss", "oss"]}
{"url": "http://www.mycsearch.com/?p=133", "timestamp": 1258433047, "tags": ["services", "email", "hosting", "hybrid", "microsoft", "dynamics", "sharepoint", "collaboration", "oracle", "salesforce.com", "sap", "wimax"]}
{"url": "http://www.sterlingedgeonline.com/industrial-laser-services", "timestamp": 1258495192, "tags": ["industrial", "cutting", "custom", "laser", "engraving", "denver", "waterjet", "services", "art", "glass", "murals", "prints", "monuments", "metal", "marking", "unique", "office", "artwork", "water", "jet", "cutter", "business", "gifts"]}
{"url": "http://www.imahollywoodstar.com/", "timestamp": 1258426519, "tags": ["song", "contest", "california", "2010", "talent", "music", "writing", "online", "singing", "competition"]}
{"url": "http://blog.fenon.com.br/artigos/dicas-e-como-engravidar-de-um-menino/", "timestamp": 1258443301, "tags": ["como", "engravidar", "menino", "dica"]}
{"url": "http://rahulmgo.wordpress.com/", "timestamp": 1258433055, "tags": ["staff", "management", "offshore", "near", "shore", "development", "support", "centers"]}
{"url": "http://www.ageeko.com/", "timestamp": 1258456351, "tags": ["utah", "computer", "repair"]}
{"url": "http://www.212articles.com/articles/70546/1/About-hazard-perception-test-part-in-DSA-drivingtheorytest/Page1.html", "timestamp": 1258422753, "tags": ["test"]}
{"url": "http://www.usabirdcontrol.com/index.asp?PageAction=VIEWPROD&ProdID=67", "timestamp": 1258429234, "tags": ["netting", "bird", "control", "repellent", "pest", "spikes"]}
{"url": "http://www.wikio.com/article/143135010", "timestamp": 1258433029, "tags": ["gateway", "technolabs", "saas", "managed", "services", "cloud", "computing", "innovation", "frameworks", "accelerators", "methodologies", "solutions", "offshore", "software", "development", "outsourcing", "web", "india", "custom", "application"]}
{"url": "http://www.onlinecancerguide.com/blog/cancer-info/17-ways-to-reduce-cancer-hazards/", "timestamp": 1258431071, "tags": ["cancer", "info", "breast", "pancreatic", "treatment", "testicular", "prostate", "radiation", "ovarian", "liver", "skin", "lung", "colon", "d", "mouth", "throat", "mesothelioma", "bone", "blood", "brain", "leukemia", "thyroid", "oral"]}
{"url": "http://www.8starshop.com/en/colorful-astro-star-space-laser-projector-cosmos-light.html", "timestamp": 1258499017, "tags": ["colorful", "astro", "star", "space", "laser", "projector", "cosmos", "light"]}
{"url": "http://synverse.blog.com/", "timestamp": 1258433054, "tags": ["tibco", "alfresco", "chordiant", "inted", "joomla", "mecrosoft", ".net", "oracle", "amdocs", "convergys", "sap", "q2a", "media", "strategic", "imperatives", "ericsson", "environment", "agency", "alaris", "cmfg"]}
{"url": "http://www.bestofindya.com/news/story.php?title=Propositions", "timestamp": 1258433048, "tags": ["bookmark", "synverse"]}
{"url": "http://customermanagementsolutions.wordpress.com/", "timestamp": 1258433057, "tags": ["tibco", "sap", "orical", "php", "synverse", "java", "enterprise", "integration", "solutions", "business", "process", "automation", "carrier", "grade", "convergent"]}
{"url": "http://videocop.com/", "timestamp": 1258444814, "tags": ["videocop"]}
{"url": "http://specialpopular.com/detail/link-11557.html", "timestamp": 1258433042, "tags": ["customer", "management", "solutions", "enterprise", "application", "integration"]}
{"url": "http://www.californiamotorcyclelaw.com/", "timestamp": 1258443175, "tags": ["california", "motorcycles", "accidents", "lawyers", "catastrophic", "injuries", "crash", "attorney", "sacramento", "crashes", "injury", "personal", "motorcycle", "attorneys", "accident", "attorneys"]}
{"url": "http://eshop.talash.com/shop/category/gift_certificates/", "timestamp": 1258421002, "tags": ["send", "india", "buy", "online", "raymond", "pantaloons", "megamart"]}
{"url": "http://blog.fenon.com.br/artigos/direitos-da-empregada-domestica/", "timestamp": 1258434666, "tags": ["carteira", "trabalho", "direitos", "empregada"]}
{"url": "http://www.earticlesonline.com/Article/GTL-Synverse-Microsoft-Managed-Services-Offerings--From-Concept-to-Implementation-till-Support/633030", "timestamp": 1258433035, "tags": ["saas", "software", "service", "platform", "enablement", "business", "paas", "blog", "apprenda", "saasgrid", "applications"]}
{"url": "http://www.mycsearch.com/?p=129", "timestamp": 1258433051, "tags": ["maidenhead", "innovative", "offering", "managed", "services", "help", "desks"]}
{"url": "http://www.wikio.com/article/133406276", "timestamp": 1258433035, "tags": ["saas", "software", "hosted", "testing", "platform"]}
{"url": "http://wimaxglobal09.eventscope.co.uk/index.php?method=showdetails&list=appuser&rollid=126431406&fromfrommethod=showhtmllist&fromfromlist=message_inbox", "timestamp": 1258433048, "tags": ["eventscope", "online", "networking", "wimax", "bss", "oss", "solutions", "emea"]}
{"url": "http://videocop.com/", "timestamp": 1258444816, "tags": ["download", "free", "dvd", "movies"]}
{"url": "http://www.youtube.com/watch?v=fkyT3o9Rm60", "timestamp": 1258489127, "tags": ["clickbank", "affiliate", "search", "products", "marketplace", "category"]}
{"url": "http://ow.ly/hM65", "timestamp": 1258433042, "tags": ["recruitment"]}
{"url": "http://www.lyco.co.uk/Light-Fittings/Indoor-Light-Fittings/Bathroom-Lighting/Shaver-Lights/sc1437/p864.aspx", "timestamp": 1258445091, "tags": ["shaver"]}
{"url": "http://www.goarticles.com/cgi-bin/showa.cgi?C=2219647", "timestamp": 1258431324, "tags": ["salvia", "dragon", "effects"]}
{"url": "http://www.2circles.com/", "timestamp": 1258433032, "tags": ["business", "telecommunications", "phones", "phone", "lines", "mobiles", "2", "circles", "communications", "cheap", "international", "0870", "0845", "telephones", "company", "phones.broadband", "internet", "access", "mobile", "deals", "mbps", "broadband"]}
{"url": "http://www.thamesvalleychamber.co.uk/directory/result.asp?act=none&KeyName=Offshore%20Services&TID=1802&Member=0", "timestamp": 1258433045, "tags": ["synverse", "limited"]}
{"url": "http://www.quiz-creator.com/articles/make-a-thanksgiving-flash-quiz.html#110", "timestamp": 1258419986, "tags": ["make", "thanksgiving", "quiz", "quizzes"]}
{"url": "http://www.lesbiandatingpersonals.com.au/blogs/index.php/some-golden-tips-for-successful-single-dating/", "timestamp": 1258424533, "tags": ["website", "singles", "date", "sites", "relationship", "online"]}
{"url": "http://blog.fenon.com.br/artigos/dicas-de-presentes-para-amigo/", "timestamp": 1258444231, "tags": ["dicas", "presente", "amigos", "ideias"]}
{"url": "http://synverse.zoomblog.com/archivo/2009/08/25/synverse-Expanding-India-Operations.html", "timestamp": 1258433039, "tags": ["golabal", "offshore", "outsourcing", "software", "development", "global", "sourcing", "custom", "business", "process", "services"]}
{"url": "http://www.synverse.com/index.php?page=business-intelligence-proposition", "timestamp": 1258433067, "tags": ["business", "intelligence", "proposition", "information", "management", "solutions", "process", "architecture"]}
{"url": "http://www.onlinecancerguide.com/blog/cancer-info/17-ways-to-reduce-cancer-hazards/", "timestamp": 1258431070, "tags": ["increase", "risks", "survive"]}
{"url": "http://www.commsbusiness.co.uk/News_Article_JS1.cfm?NewsID=8648", "timestamp": 1258433044, "tags": ["data", "telephones", "alcatel", "avaya", "aastra", "samsung", "toshiba", "panasonic", "bt", "lg"]}
{"url": "http://www.synverse.com/index.php?page=frameworks", "timestamp": 1258433065, "tags": ["technology", "frameworks"]}
{"url": "http://granite-countertops-toronto.blogspot.com/", "timestamp": 1258433613, "tags": ["granite", "countertops", "toronto"]}
{"url": "http://downloadpreciousfullmovie.weebly.com/", "timestamp": 1258450407, "tags": ["download", "precious", "watch", "movie", "online"]}
{"url": "http://www.synverse.com/index.php?page=industries", "timestamp": 1258433070, "tags": ["solutions"]}
{"url": "http://www.slideshare.net/synverse/synverse-corporate-overview", "timestamp": 1258433030, "tags": ["oracle", "peoplesoft", "siebel", "chordiant", "jd", "edwards", "sap", "webmethods", "tibco", "ibm", "wbi", "bea", "wli", "biztalk", "server", "broker", "technologies", "like", "jms", "asp.net", "c#", "vb.net", "xml"]}
{"url": "http://www.bigrigattorneys.com/", "timestamp": 1258443234, "tags": ["lawyers", "attorneys", "crashes", "injury", "motor", "vehicle", "trucking"]}
{"url": "http://www.planningbride.com/", "timestamp": 1258492341, "tags": ["planning", "bride", "wedding", "planner", "plan"]}
{"url": "http://www.212articles.com/articles/69644/1/DSA-Driving-Theory-Test-For-Car-And-BikeLearner-Drivers--Hazard--Perception-Test-/Page1.html", "timestamp": 1258422681, "tags": ["hazard", "perception", "test", "clips"]}
{"url": "http://www.academicstudies.com/why_choose.html", "timestamp": 1258440851, "tags": ["study", "abroad", "programs", "summer"]}
{"url": "http://blog.fenon.com.br/artigos/dicas-de-maquiagem-para-casamento/", "timestamp": 1258445320, "tags": ["dicas", "maquiagem", "casamento"]}
{"url": "http://tibcos.wordpress.com/", "timestamp": 1258433055, "tags": ["tibco", "sap", "bea", "mq", "oracle", "hordiant", "seibel", "php", "java", "joomla", "j2ee", ".net", "cake", "bpo"]}
{"url": "http://www.webinfology.com/", "timestamp": 1258438136, "tags": ["cakephp", "solutions", "india", "indian", "joomla", "development", "company", "drupal", "firm", "noida", "delhi", "zen", "cart", "smarty", "mvc", "graphic", "designing", "offshore", "staffing", "dynamic", "web", "application", "php", "seo", "services"]}
{"url": "http://www.rhapsodomancy.com/natural-cellulite-treatment-a-new-step/", "timestamp": 1258424341, "tags": ["health", "cellulite", "treatment", "medicine"]}
{"url": "http://www.outlookexpress-repair.net/buy-outlook-express-repair.php", "timestamp": 1258434760, "tags": ["outlook", "express", "repair", "fix", "tool"]}
{"url": "http://www.freshcouponcodes.com/", "timestamp": 1258502326, "tags": ["code", "discount", "online", "promotional", "printable", "free", "shipping", "vouchers", "promo", "deals"]}
{"url": "http://en.wikipedia.org/wiki/NaviSite", "timestamp": 1258447471, "tags": ["navisite", "hosting", "services", "solutions", "web", "cloud", "enterprise", "wikipedia", "email", "navicloud", "jobs", "careers"]}
{"url": "http://www.goldenpetsupplies.com/", "timestamp": 1258447189, "tags": ["goldenpetsupplies.com", "organic", "pet", "supplies", "natural", "online", "gourmet", "treats", "toys", "grooming", "products", "vitamins", "gifts", "dog", "lovers"]}
{"url": "http://freecallindia.org/free-mobile-call-india", "timestamp": 1258501825, "tags": ["free", "mobile", "india"]}
{"url": "http://www.alaska-defensivedriving.com/alaska-traffic-school.html", "timestamp": 1258428288, "tags": ["alaska", "traffic", "school", "defensive", "driving", "course", "ticket."]}
{"url": "http://www.friesland-kleinanzeiger.de/", "timestamp": 1258454432, "tags": ["friesland-kleinanzeiger", "anzeigenmarkt", "verkaufen", "kaufen", "tauschen", "anzeiger", "kleinanzeiger", "kostenlos", "inserat", "anzeigen"]}
{"url": "http://www.synverse.com/index.php?page=site-map", "timestamp": 1258433057, "tags": ["wlr3", "wimax", "3g", "voip", "m-commerce", "self", "care", "retail", "point", "sale", "product", "catalogue", "oracle", "telecommunication", "solutions", "enterprise", "resource", "planning", "application", "integration", "information", "technology", "services", "outsourcing", "consulting", "offshoring", "generation", "bss", "oss", "methodology", "qa", "intellectual", "property"]}
{"url": "http://exchange-server-support.blogspot.com/", "timestamp": 1258418346, "tags": ["server", "support", "exchange", "microsoft"]}
{"url": "http://trydunlo.yourkwagent.com/", "timestamp": 1258456587, "tags": ["virginia", "beach", "real", "estate"]}
{"url": "http://www.lumeprints.com/", "timestamp": 1258421251, "tags": ["black", "white", "photography", "canvas", "art", "prints", "landscape", "nature", "wall", "art."]}
{"url": "http://allindiagifts.com/shop/category/dinner_gift_vouchers/", "timestamp": 1258421194, "tags": ["dinner", "gift", "vouchers", "send", "india", "buy", "online", "gifts", "mumbai", "delhi", "bangalore", "food", "unique"]}
{"url": "http://www.easyrent.ca/tenants.asp", "timestamp": 1258451357, "tags": ["vancouver", "house", "rental", "rent", "furnished", "apartments", "condos", "apartment", "rentals", "unfurnished"]}
{"url": "http://www.airedaledirectory.com/detail/link-23613.html", "timestamp": 1258433048, "tags": ["application", "crm", "enterprise", "erp", "process", "proposition", "sap", "scm", "solutions", "synverse", "technology", "tibco"]}
{"url": "http://www.pixpod.com/", "timestamp": 1258438136, "tags": ["pixpod", "photo", "booth", "hire", "rent", "party", "digital", "booths", "rental"]}
{"url": "http://www.squidoo.com/ufc-106-free-live-stream", "timestamp": 1258459916, "tags": ["ufc", "106", "free", "live", "stream", "ortiz", "vs", "griffin"]}
{"url": "http://www.synverse.com/index.php?page=synverse-integration-framework", "timestamp": 1258433051, "tags": ["terminology", "service", "store", "integration", "framework", "sif", "data", "facility", "middleware", "retail", "software", "soa", "service-oriented", "architecture", "pos", "application"]}
{"url": "http://www.essaycapital.com/blog/all-about-essay/admesy/886", "timestamp": 1258433311, "tags": ["writing", "admission", "good"]}
{"url": "http://www.seovoter.com/upcoming", "timestamp": 1258433032, "tags": ["onlywire"]}
{"url": "http://www.synverse.com/index.php?page=frameworks", "timestamp": 1258433066, "tags": ["industry", "project", "implementation", "solution", "testing", "monitoring", "integration", "webcore"]}
{"url": "http://www.synverse.com/index.php?page=enterprise-application-solution", "timestamp": 1258433067, "tags": ["enterprise", "application", "solutions", "proposition", "process", "erp", "crm", "scm"]}
{"url": "http://www.ebest24.co.uk/2-x-194-501-921-t10-w5w-4-led-smd-white-xenon-bulb-904-3436.html", "timestamp": 1258494234, "tags": ["t10", "w5w", "4led", "smd", "xenon", "bulb", "194", "501", "921"]}
{"url": "http://www.halongluxurytravel.com/", "timestamp": 1258424628, "tags": ["halong", "bay", "quang", "ninh", "vietnam", "travel"]}
{"url": "http://www.gatewaytechnolabs.com/lang,en/partners_affiliates.html", "timestamp": 1258433039, "tags": ["anuj", "sachdeva", "partners", "affiliates", "for:albany", "for:kingdom", "for:limited", "for:market", "for:sl6", "for:synverse", "for:united"]}
{"url": "http://www.voipsolutions.com.au/", "timestamp": 1258494128, "tags": ["cheap", "calls", "cisco", "phones", "hosted", "pabx", "ip", "pbx", "phone", "systems", "telephony", "voice", "voip", "solutions", "telephone."]}
{"url": "http://www.sparsh-technologies.com/web-development-services/custom-application-development.php", "timestamp": 1258433777, "tags": ["custom", "application", "development", "bespoke", "web", "maintenance", "website"]}
{"url": "http://www.live-pr.com/en/synverse-and-gateway-technolabs-partner-r1048323519.htm", "timestamp": 1258433038, "tags": ["gateway", "technolabs", "partner", "anuj", "sachdeva", "ceo", "saas", "cloud", "computing"]}
{"url": "http://www.tcbyfranchise.com/", "timestamp": 1258492447, "tags": ["yogurt", "franchise", "tcby", "probiotics", "sorbet", "frappe", "chiller", "cappuccino", "frozen", "coffee", "cakes", "pies", "frozens"]}
{"url": "http://blog.fenon.com.br/artigos/dicas-para-decorar-quartos-de-meninas-e-meninos/", "timestamp": 1258440816, "tags": ["meninos", "meninas", "decorar", "quarto"]}
{"url": "http://www.phoenix-personalinjuryattorney.com/practiceareas/", "timestamp": 1258443584, "tags": ["miller", "pitt"]}
{"url": "http://freecallindia.org/free-mobile-calls-to-india", "timestamp": 1258501915, "tags": ["free", "mobile", "india"]}
{"url": "http://www.allindiagifts.com/shop/category/apparels_&_accessories/", "timestamp": 1258421157, "tags": ["buy", "clothes", "online", "apparel", "accessories", "india", "shopping", "apparels", "&", "designer", "send", "mumbai", "delhi", "hyderabad", "clothing", "womens", "mens", "ladies", "wear"]}
{"url": "http://www.synverse.com/index.php?mact=News,cntnt01,detail,0&cntnt01articleid=1&cntnt01returnid=59", "timestamp": 1258433063, "tags": ["partners", "partnership", "zephyr", "point", "telco", "boss", "customers", "leaders", "solution", "development"]}
{"url": "http://www.commsbusiness.co.uk/News_Article_JS1.cfm?NewsID=8648", "timestamp": 1258433043, "tags": ["channel", "awards", "voice"]}
{"url": "http://www.krystal-limousines.co.uk/", "timestamp": 1258456361, "tags": ["nottingham", "limosine", "stretch", "west", "midlands"]}
{"url": "http://www.nicollracingonlinestore.com/", "timestamp": 1258456558, "tags": ["motorcycle", "repair", "orange", "county"]}
{"url": "http://searcharticles.net/article.cfm/id/176752", "timestamp": 1258433036, "tags": ["saas", "business", "consultancy", "enterprise"]}
{"url": "http://www.christianfea.com/joint-ventures/to-be-successful-in-a-jv-you-must-learn-to-share/", "timestamp": 1258481687, "tags": ["business", "entrepreneur", "money", "clients", "marketing"]}
{"url": "http://www.prlog.org/10305655-synverse-expanding-india-operations.html", "timestamp": 1258433041, "tags": ["bpo", "services", "helpdesk", "india", "business", "process", "outsourcing", "support"]}
{"url": "http://sendgifts2india.com/shop/category/dinner_gift_vouchers/", "timestamp": 1258421086, "tags": ["dinner", "gift", "vouchers", "send", "gifts", "india", "certificates", "dominos", "voucher", "tian", "restobar", "unique", "online", "shopping", "rajwadu"]}
{"url": "http://www.technologyworld09.com/visit_the_show/company_profile.aspx?CompanyID=6852", "timestamp": 1258433029, "tags": ["saas", "parallels", "software", "service", "applications", "outsourcing", "asp", "bpo", "msp", "elp", "desk", "management", "solution", "axios", "systems", "best", "practice", "itsm"]}
{"url": "http://www.1888pressrelease.com/synverse-expanding-its-sap-footprint-pr-119052.html", "timestamp": 1258433049, "tags": ["sap", "tibco", "australia", "india", "countries"]}
{"url": "http://watch2012movie.weebly.com/", "timestamp": 1258450331, "tags": ["download", "2012", "watch", "movie", "online"]}
{"url": "http://www.techprspider.com/Synverse-Expanding-India-Operations-feed26915.aspx", "timestamp": 1258433042, "tags": ["sap", "q2a", "media", "strategic", "imperatives", "ericsson", "environment", "agency", "alaris", "cmfg", "tansplus", "wolters", "kluwer", "zham", "pinnacle", "industry", "domain", "telco", "telecommunication"]}
{"url": "http://www.synverse.com/", "timestamp": 1258432665, "tags": ["saas", "security", "business", "exchange", "intelligence", "online", "platform", "subscription", "payments", "uk", "review", "model", "development", "hosting", "crm", "web", "implementation"]}
{"url": "http://www.california-auto-accidents.com./", "timestamp": 1258443057, "tags": ["santa", "clara", "mendocino", "modoc", "napa", "nevada", "placer", "plumas", "san", "francisco", "juaquin", "mateo", "shasta", "sierra", "siskiyou", "solano", "sonoma", "tehama", "trinity", "yolo", "yuba", "bay", "area", "stockton", "modesto", "folsom", "woodland", "vacaville", "fairfield", "vallejo", "placerville", "grass", "valley", "city", "roseville", "concord"]}
{"url": "http://downloadthefourthkindmovieonline.weebly.com/", "timestamp": 1258450372, "tags": ["watch", "fourth", "kind"]}
{"url": "http://www.synverse.com/index.php?page=technology-infrastructure", "timestamp": 1258433067, "tags": ["infrastructure", "management", "proposition", "services", "enterprise", "tibco"]}
{"url": "http://www.mozilla.com/en-GB/firefox/about/", "timestamp": 1258501604, "tags": ["mozilla", "firefox"]}
{"url": "http://ayurvedic.org/", "timestamp": 1258425932, "tags": ["ayurveda", "ayurvedic", "treatment"]}
{"url": "http://www.slideshare.net/synverse/synverse-corporate-overview", "timestamp": 1258433032, "tags": ["development", "2.0", "advanced", "dynamic", "websites", "website", "design", "redesign", "intranet", "extranet", "portal", "content", "management", "solution", "seo", "services", "hosting"]}
{"url": "http://www.4yousoft.com/flip/flip-video-converter-mac.htm", "timestamp": 1258447954, "tags": ["flip", "video", "converter", "mac", "convert", "imovie", "final", "cut", "pro", "express", "free", "download"]}
{"url": "http://www.synverse.com/index.php?page=retail-distribution", "timestamp": 1258433064, "tags": ["synverse", "retail", "&", "distribution", "practice", "supply", "chain", "warehousing", "services", "solutions"]}
{"url": "http://www.amazonacaiberry.com/", "timestamp": 1258416053, "tags": ["acai", "berry", "health", "care"]}
{"url": "http://www.synverse.com/index.php?page=synverse-testing-framework", "timestamp": 1258433051, "tags": ["tibco", "bea", "mq", "oracle", "sap", "chordiant", "seibel", "php", "java", "joomla"]}
{"url": "http://cibol.net/", "timestamp": 1258501306, "tags": ["chandigarh", "erp", "solutions", "customized"]}
{"url": "http://www.1888pressrelease.com/synverse-global-expertise-in-deployment-support-services-f-pr-158705.html", "timestamp": 1258433032, "tags": ["synverse", "gateway", "technolabs", "saas", "managed", "services", "cloud"]}
{"url": "http://professionalclick.com/", "timestamp": 1258438136, "tags": ["indian", "professionals", "jobs", "services", "specialised", "classified", "delhi", "consultancy", "india", "online", "job", "profile", "professional", "company"]}
{"url": "http://www.shekaf.com/revitol-best-anti-cellulite-cream/", "timestamp": 1258429241, "tags": ["health", "medicine", "treatment"]}
{"url": "http://webdirectorie.com/computers-and-internet/software/", "timestamp": 1258433053, "tags": ["solutions", "b2b"]}
{"url": "http://www.4mat4business.com/", "timestamp": 1258456251, "tags": ["train", "trainer"]}
{"url": "http://www.seovoter.com/submit", "timestamp": 1258433032, "tags": ["onlywire"]}
{"url": "http://www.pcoptimizerpro.net/", "timestamp": 1258422981, "tags": ["startup", "manager", "programs", "windows"]}
{"url": "http://www.seenation.com/view_full_news_details.php?newsid=124705&title=Synverse%20and%20Gateway%20Technolabs%20Partner%20to%20provide%20end2end%20Implementation%20and%20Managed%20Services", "timestamp": 1258433037, "tags": ["development", "india", "custom", "application", "global"]}
{"url": "http://www.information-online.com/node/21350", "timestamp": 1258433033, "tags": ["global", "expertise", "solution", "capabilities", "uk", "trade", "new", "mobile", "broadband", "services", "seacom", "fibre"]}
{"url": "http://www.synverse.com/index.php?page=partners", "timestamp": 1258433063, "tags": ["partners", "partnership", "zephyr", "point", "telco", "boss", "customers", "leaders", "solution", "development"]}
{"url": "http://web-master-directory.com/details.php?id=10015", "timestamp": 1258433048, "tags": ["tibco", "chordiant", "practice", "global", "delivery", "offshoring", "outsourcing", "driven", "methodologies", "accelerators", "frameworks", "end", "telco", "bss", "content", "management", "ecommerce"]}
{"url": "http://www.mapsofworld.com/botswana/hotels/", "timestamp": 1258420479, "tags": ["botswana", "hotels"]}
{"url": "http://www.synverse.com/index.php?page=terms-of-use", "timestamp": 1258433058, "tags": ["oracle", "sap", "chordiant", "seibel", "php", "java", "joomla", "j2ee", ".net", "cake", "domain", "consulting", "bpo", "crm", "eai", "testing", "quality", "assurance", "erp"]}
{"url": "http://blogs.synverse.com/synapse/home/", "timestamp": 1258433059, "tags": ["sitepoint"]}
{"url": "http://www.boobelly.com/info/7291.html", "timestamp": 1258433050, "tags": ["boobelly", "seo"]}
{"url": "http://rahulmgo.wordpress.com/", "timestamp": 1258433054, "tags": ["global", "operations", "marketing", "project", "staffing", "logistics", "emea"]}
{"url": "http://24x7-server-support.blogspot.com/", "timestamp": 1258418980, "tags": ["24/7", "server", "support"]}
{"url": "http://www.synverse.com/index.php?page=careers", "timestamp": 1258433060, "tags": ["business", "solutions", "enterprise", "integration", "process", "management", "intelligence", "data", "warehousing", "collaboration", "social", "networking", "open", "source", "bss", "messaging", "monitoring"]}
{"url": "http://www.synverse.com/index.php?page=terms-of-use", "timestamp": 1258433057, "tags": ["tibco", "bea", "mq"]}
{"url": "http://www.rajasthantoursonline.com/tours/exotic-rajasthan-tour.htm", "timestamp": 1258419965, "tags": ["rajasthan", "exotic", "tours", "tour"]}
{"url": "http://www.synverse.com/index.php?page=moral-fibre", "timestamp": 1258433061, "tags": ["domain", "consulting", "bpo", "crm", "eai", "testing", "quality", "assurance", "erp"]}
{"url": "http://www.quiz-creator.com/blog/2009/11/track-online-learning-quality-at-h1n1-period", "timestamp": 1258419962, "tags": ["make", "thanksgiving", "quiz", "quizzes"]}
{"url": "http://www.freepressrelease.com.au/ShowFull.asp?date=17626", "timestamp": 1258433045, "tags": ["iso", "9001", "2008", "certification"]}
{"url": "http://www.phutoan.com.vn/", "timestamp": 1258424272, "tags": ["th\u1ecb"]}
{"url": "http://www.pedcoengines.com/dieselengines.html", "timestamp": 1258418354, "tags": ["remanufactured", "marine", "engines", "dual", "fuel"]}
{"url": "http://www.nationalarcaderentals.com/", "timestamp": 1258451399, "tags": ["arcade", "game", "rentals", "video", "rental", "event", "planning", "team", "building"]}
{"url": "http://www.seatcoverdeals.com/", "timestamp": 1258427200, "tags": ["seat", "covers", "car", "custom", "waterproof", "coverking"]}
{"url": "http://www.trident-insurance.co.uk/index.php", "timestamp": 1258442808, "tags": ["cheap", "commercial", "insurance", "vehicle"]}
{"url": "http://www.freshcouponcodes.com/", "timestamp": 1258502325, "tags": ["coupon", "codes", "coupons"]}
{"url": "http://www.newdesignworld.com/press/story/17604", "timestamp": 1258433045, "tags": ["iso", "9000", "9001", "9004:2000", "quality", "management", "systems", "guidelines", "performance", "improvements", "9002", "9003"]}
{"url": "http://www.mycsearch.com/?p=133", "timestamp": 1258433046, "tags": ["managed"]}
{"url": "http://www.vivaladeals.com/", "timestamp": 1258430163, "tags": ["ipod", "accessories", "iphone", "tv", "wall", "mounts", "lcd"]}
{"url": "http://www.reading.ac.uk/careers/jobs/info.asp?id=9219", "timestamp": 1258433054, "tags": ["business", "development", "associate", "sales", "marketing", "jobs", "job", "uk", "london"]}
{"url": "http://www.onlineprnews.com/news/6819-1253616024-synverse-and-gateway-technolabs-partner-to-provide-end2end-implementation-and-managed-services.html", "timestamp": 1258433038, "tags": ["offshore", "software", "development", "outsourcing", "web", "india", "services", "custom", "application"]}
{"url": "http://www.prfocus.com/article/Synverse_Limited_Headquarters_Opening_Ceremony__17748.html", "timestamp": 1258433054, "tags": ["tibco", "achievements", "products", "infrastructure", "management", "business", "intelligence"]}
{"url": "http://www.essaycapital.com/blog/all-about-essay/history-essay/926", "timestamp": 1258433761, "tags": ["history", "essay", "writing", "research", "papers", "term", "assignments", "citing", "sources", "academic", "assignment"]}
{"url": "http://www.woodwormcricketbats.net/", "timestamp": 1258488355, "tags": ["woodworm", "cricket", "bat", "bats"]}
{"url": "http://www.offshoreaccountingtaxation.com/", "timestamp": 1258501333, "tags": ["bookkeeping", "accounting"]}
{"url": "http://wimaxglobal09.eventscope.co.uk/index.php?method=showdetails&list=appuser&rollid=126431406&fromfrommethod=showhtmllist&fromfromlist=message_inbox", "timestamp": 1258433049, "tags": ["wimaxglobal09", "uk"]}
{"url": "http://www.1888pressrelease.com/synverse-and-gateway-technolabs-partner-to-provide-end2end-i-pr-152691.html", "timestamp": 1258433036, "tags": ["offshore", "software", "development", "outsourcing", "web", "india", "services", "custom", "application"]}
{"url": "http://www.free-press-release.com/news/200908/1249902603.html", "timestamp": 1258433039, "tags": ["custom", "application"]}
{"url": "http://www.prlog.org/10354231-synverse-and-gateway-technolabs-partner-to-provide-end2end-implementation-and-managed-services.html", "timestamp": 1258433038, "tags": ["offshore", "software", "development", "outsourcing", "web", "india", "services", "custom", "application"]}
{"url": "http://www.viatoura.de/heidepark-soltau.html", "timestamp": 1258451221, "tags": ["heidepark", "erlebnispark", "online", "soltau", "park"]}
{"url": "http://blog.fenon.com.br/artigos/dicas-de-como-ser-modelo-fotografico-e-passarela/", "timestamp": 1258446743, "tags": ["desfilar", "aula", "etiquetas", "concursos"]}
{"url": "http://www.synverse.com/index.php?page=finance-banking", "timestamp": 1258433064, "tags": ["synverse", "finance", "&", "banking", "practice", "services", "solutions", "business", "markets", "application"]}
{"url": "http://www.synverse.com/index.php?page=business-process-outsourcing-proposition", "timestamp": 1258433052, "tags": ["bpo", "center", "centers", "medical", "transcription", "india", "centres", "outsourcing", "coding", "recruitment", "process"]}
{"url": "http://www.synverse.com/index.php?page=corporate-overview", "timestamp": 1258433061, "tags": ["industry", "domain", "telco", "telecommunication", "telecoms", "health", "banking", "retail", "life", "sciences", "finance", "tibco", "bea", "mq", "oracle", "sap", "chordiant", "seibel", "php", "java", "joomla", "j2ee", ".net", "cake", "consulting", "bpo", "crm", "eai", "testing", "quality", "assurance", "erp"]}
{"url": "http://www.212articles.com/articles/40198/1/Synverse-expanding-its-SAP-footprint/Page1.html", "timestamp": 1258433050, "tags": ["world-class", "solutions", "sap", "implementation", "services", "infrastructure", "management", "post-sap", "extension", "integration", "upgrade", "consolidation"]}
{"url": "http://www.openpr.com/news/89365/Synverse-Attains-ISO-9001-Certification.html", "timestamp": 1258433042, "tags": ["synverse", "attains", "iso", "9001", "certification", "9000", "9004:2000", "quality", "management", "systems", "guidelines", "performance", "improvements", "9002", "9003"]}
{"url": "http://www.networldsolutions.org/", "timestamp": 1258438138, "tags": ["web", "india", "promotion", "delhi", "website", "seo", "company", "indian", "firm", "php", "developers", "programmer", "designer", "marketing", "search", "engine", "pay", "click", "advertising"]}
{"url": "http://downloadtheboondocksaints2allsai.weebly.com/", "timestamp": 1258450622, "tags": ["download", "boondock", "saints", "2", ":", "day"]}
{"url": "http://reverseip.in/", "timestamp": 1258422688, "tags": ["reverse", "ip", "lookup"]}
{"url": "http://www.articlebasement.com/articles/84181/1/GTL-Synverse-Microsoft-Managed-Services-Offerings-From-Concept-to-Implementation-till-Support/Page1.html", "timestamp": 1258433036, "tags": ["offshore", "software", "development", "outsourcing", "web", "india", "services", "custom", "application"]}
{"url": "http://www.1888pressrelease.com/synverse-expanding-india-operations-pr-141217.html", "timestamp": 1258433039, "tags": ["telco", "enterprise", "saas", "migration", "benefits", "vendors", "application", "examples", "moving", "microsoft", "solution", "offering", "applications", "securit"]}
{"url": "http://www.30dayloans.me/", "timestamp": 1258430127, "tags": ["payday", "cash", "online", "money", "credit", "internet", "finance", "loans", "fast", "easy"]}
{"url": "http://www.fakefurfashion.co.uk/", "timestamp": 1258438135, "tags": ["fur", "clothes", "products", "garment", "woven", "fashion", "furs", "fine", "fox", "coats"]}
{"url": "http://www.synverse.com/index.php?page=enterprise-business-integration-proposition", "timestamp": 1258433067, "tags": ["enterprise", "business", "integration", "proposition", "process", "standards", "webmethods", "tibco", "ibm", "wbi", "sap", "oracle", "bea", "wli", "biztalk", "server", "peoplesoft"]}
{"url": "http://eshop.talash.com/shop/category/dinner_gift_vouchers/", "timestamp": 1258420969, "tags": ["dinner", "vouchers", "send", "india", "buy", "gift", "online", "uk", "australia", "gifts", "free", "shipping", "cheap"]}
{"url": "http://www.synverse.com/index.php?page=about-us", "timestamp": 1258433061, "tags": ["synverse", "generation", "industry", "global", "delivery", "outsourcing", "offshoring", "methodology", "frameworks", "innovation", "domain", "telco", "telecommunication", "telecoms"]}
{"url": "http://somadrug.com/", "timestamp": 1258444892, "tags": ["pornkeeper", "free", "porn", "videos", "download", "adult", "movies"]}
{"url": "http://pages.citebite.com/h1g7d3d2u1lgi", "timestamp": 1258433039, "tags": ["golabal", "offshore", "outsourcing", "software", "development", "global", "sourcing", "custom", "business", "process", "services"]}
{"url": "http://www.essentialoilsonline.co.uk/acatalog/massage_oils.html", "timestamp": 1258431865, "tags": ["massage", "oils"]}
{"url": "http://www.memoryfoammattresszleeps.co.uk/4ft-double-bed-special-offer.html", "timestamp": 1258425336, "tags": ["4ft", "double", "bed"]}
{"url": "http://www.information-online.com/node/21350", "timestamp": 1258433035, "tags": ["wimax", "links", "forum", "provides", "business", "consulting", "systems", "integration", "crm", "bss", "oss", "implementation", "outsourced", "testing", "web", "portal", "development", "cloud"]}
{"url": "http://leeloveshottrends.com/beyonce-and-lady-gaga-video-phone-remix-video", "timestamp": 1258445134, "tags": ["beyonce", "lady", "gaga", "new", "video", "feat", "agga", "featuring", "phone", "music", "remix"]}
{"url": "http://sendgifts2india.com/shop/category/apparels_&_accessories/", "timestamp": 1258421038, "tags": ["send", "apparels", "india", "accessories", "gifts", "buy", "online", "womens", "wedding", "wear", "mens", "ladies", "shopping"]}
{"url": "http://www.youtube.com/watch?v=sH-hDrH-fS0", "timestamp": 1258490681, "tags": ["canine", "aggression", "training", "stop", "aggressive", "behavior", "canines"]}
{"url": "http://www.pressreleasepoint.com/synverse-attains-iso-9001-certification", "timestamp": 1258433045, "tags": ["iso", "9001", "certification", "2008"]}
{"url": "http://fivestarhotelresort.blogspot.com/2009/11/great-adventure-with-perfect-cruise.html", "timestamp": 1258423206, "tags": ["online", "cruise"]}
{"url": "http://www.reise-organizer.de/", "timestamp": 1258483429, "tags": ["minute", "urlaub", "pauschalreisen", "lastminute", "reise", "reisen", "ferien", "familienreise", "familienurlaub", "cluburlaub", "singlereise", "singleurlaub", "rundreise", "fernreise", "reiseangebote", "angebote", "flug", "flieger", "hotel", "hotels", "mietwagen", "billig", "preiswert", "g\u00fcnstig"]}
{"url": "http://www.telecommentor.com/jobs/job/2688/telecom-testers-at-synverse/", "timestamp": 1258433053, "tags": ["unix", "skills", "oracle", "xml", "soap"]}
{"url": "http://www.handloommark.gov.in/gallery.aspx", "timestamp": 1258441733, "tags": ["handloom", "mark", "cluster", "seminar", "exhibition", "trade", "fairs", "expo", "fair"]}
{"url": "http://www.synverse.com/index.php?page=web-engineering-proposition", "timestamp": 1258433067, "tags": ["synverse", "web", "engineering", "proposition", "application", "ecommerce", "technology", "open", "source", "content", "management", "rich", "internet"]}
{"url": "http://www.balkanupdate.com/first-steps-for-cellulite/", "timestamp": 1258425388, "tags": ["health", "medicine", "treatment"]}
{"url": "http://www.synverse.com/", "timestamp": 1258432664, "tags": ["telco", "enterprise", "provider", "pricing", "news", "email", "consultancy", "vendor", "payment", "architecture", "services", "delivery", "hyderabad", "companies", "project", "reseller", "india", "erp", "consulting", "integration", "solutions", "european", "suppliers", "design", "europe", "strategy"]}
{"url": "http://www.essaycapital.com/blog/all-about-essay/shkspr/911", "timestamp": 1258433604, "tags": ["essay", "shakespeares", "plays", "writing", "write", "assignments", "research", "paper", "projects", "shakespeare", "essays"]}
{"url": "http://www.synverse.com/index.php?page=quality-analysis-proposition", "timestamp": 1258433067, "tags": ["quality", "analysis", "testing", "proposition", "software"]}
{"url": "http://www.mozilla.com/en-GB/firefox/community/", "timestamp": 1258501604, "tags": ["mozilla", "firefox"]}
{"url": "http://www.california-auto-accidents.com./", "timestamp": 1258443055, "tags": ["lawyers", "automobiles", "demas", "rosenthal", "john", "david", "law", "trial", "motor", "vehicles", "alameda", "amador", "butte", "calaveras", "colusa", "contra", "costa", "del", "norte", "el", "dorado", "glenn", "humboldt", "lake", "lassen", "marin"]}
{"url": "http://pameranjakarta.blogspot.com/2009/11/bursa-kerja-disnakertrans-visijobs.html", "timestamp": 1258459929, "tags": ["bursa", "kerja"]}
{"url": "http://www.iyogi.net/install-software.html", "timestamp": 1258425041, "tags": ["install", "software", "installation", "remote", "windows", "microsoft"]}
{"url": "http://www.ukinvest.gov.uk/OurWorld/4043591/en-GB.html", "timestamp": 1258433055, "tags": ["job", "jobs", "industry", "tibco", "sap", "solutions", "services", "europe", "companies", "uk", "employed", "technologies", "achievements", "products"]}
{"url": "http://www.freevoipcalls.org/2009/11/earthcaller-voip-from-jaduka-to-make.html", "timestamp": 1258449607, "tags": ["conference", "calling", "earthcaller", "download", "voip", "free", "international", "calls", "jaduka", "companies", "services"]}
{"url": "http://bbs.in.88db.com/", "timestamp": 1258445593, "tags": ["automobiles", "car", "reviews", "bike", "latest", "movies", "films", "cell", "phones", "mobile", "phone", "laptops", "pc", "&", "desktops", "health", "forums", "hollywood", "bollywood", "cars", "bikes", "music", "discussion", "forums."]}
{"url": "http://www.injury-attorneys.com/", "timestamp": 1258444602, "tags": ["sacramento", "lawyers", "personal", "injury"]}
{"url": "http://www.pixpod.co.uk/", "timestamp": 1258438136, "tags": ["photo", "booth", "hire", "london", "party"]}
{"url": "http://www.joshuabell.com/user/ittrainingcourse", "timestamp": 1258423800, "tags": ["course"]}
{"url": "http://www.slideshare.net/synverse/synverse-corporate-overview", "timestamp": 1258433031, "tags": ["integration", "html", "perl", "access", "database", "e-commerce", "solutions", "custom", "web", "application"]}
{"url": "http://www.lesbiandatingpersonals.com.au/blogs/index.php/some-golden-tips-for-successful-single-dating/", "timestamp": 1258424534, "tags": ["dating", "personals", "free", "internet", "single"]}
{"url": "http://www.oleolefootball.com/fixtures-la-liga/real_madrid_v_racing_santander_live.html", "timestamp": 1258500923, "tags": ["real", "madrid", "v", "racing", "santander", "live"]}
{"url": "http://www.oncloudcomputing.com/en/2009/08/it-global-managed-services-provider-driven-by-saas-and-cloud-computing-differentiators-announces-expansion/", "timestamp": 1258433036, "tags": ["andhra", "pradesh", "anuj", "sachdeva", "ceo", "synverse", "technologies", "coo", "hyderabad", "india", "global", "managed", "services", "cloud", "computing", "saas", "sudeesh", "dodda", "synverse.com", "uk"]}
{"url": "http://www.212articles.com/articles/70546/1/About-hazard-perception-test-part-in-DSA-drivingtheorytest/Page1.html", "timestamp": 1258422754, "tags": ["hazard", "perception", "clips"]}
{"url": "http://www.kioscodvd.es/shop/article_000011/Hamlet,-el-honor-de-la-venganza.html?shop_param=cid%3D1%26aid%3D000011%26", "timestamp": 1258469852, "tags": ["mel", "gibson", "glenn", "close", "alan", "bates", "helena", "bonham", "carter", "rey", "dinamarca", "muere", "viuda", "cine", "historia", "hamlet", "shakespeare", "literatura", "kioscodvd", "comprar", "online", "tienda", "dvd"]}
{"url": "http://nytails.com/", "timestamp": 1258456466, "tags": ["dog", "walking", "new", "york"]}
{"url": "http://blog.fenon.com.br/artigos/dicas-ideias-e-sugestoes-de-fantasia-para-o-carnaval/", "timestamp": 1258441780, "tags": ["carnaval", "dicas", "ideias", "fantasia"]}
{"url": "http://www.pressreleasepoint.com/synverse-managed-service-proposition-isv%E2%80%99s-reducing-operating-cost-50%E2%80%9D", "timestamp": 1258433048, "tags": ["anuj", "sachdeva", "director", "synverse", "organization", "improved", "services", "reduction", "opex", "optimization", "capex", "network", "performance"]}
{"url": "http://find4sites.com/", "timestamp": 1258438138, "tags": ["directory", "india", "trade", "importers", "exporters", "indian", "b2b", "delhi", "manufacturers", "b2c", "supplier", "portal", "market", "place"]}
{"url": "http://www.2circles.com/", "timestamp": 1258432616, "tags": ["business", "telecommunications", "phones", "phone", "lines", "mobiles", "2", "circles", "communications", "cheap", "international", "0870", "0845", "telephones", "company", "phones.broadband", "internet", "access", "mobile", "deals", "mbps", "broadband", "domain", "services", "equipment", "free"]}
{"url": "http://www.amazines.com/article_detail.cfm/888331?articleid=888331", "timestamp": 1258433048, "tags": ["sap", "implementation", "articles", "services", "infrastructure", "management", "post-sap", "extension", "integration", "upgrade", "consolidation"]}
{"url": "http://tibco-java.blogspot.com/", "timestamp": 1258433055, "tags": ["telecommunication", "tibco", "sap", "working"]}
{"url": "http://eshop.talash.com/shop/category/apparels_&_accessories/", "timestamp": 1258420931, "tags": ["send", "apparels", "india", "buy", "wear", "online", "wedding", "chaniya", "choli", "kurtas", "sarees"]}
{"url": "http://www.synverse.com/index.php?page=synverse-testing-framework", "timestamp": 1258433052, "tags": ["j2ee", ".net", "cake", "domain", "consulting", "bpo", "testing", "framework"]}
{"url": "http://www.alistdirectory.com/index.php?q=tibco", "timestamp": 1258433045, "tags": ["tibco", "software", "solutions"]}
{"url": "http://www.synverse.com/index.php?mact=News,cntnt01,detail,0&cntnt01articleid=6&cntnt01returnid=15", "timestamp": 1258433044, "tags": ["iso"]}
{"url": "http://www.sparsh-technologies.com/web-development-services/web-development.php", "timestamp": 1258433710, "tags": ["web", "development", "services", "company", "india", "website", "firm", "design"]}
{"url": "http://hi-techappliancerepair.com/", "timestamp": 1258443659, "tags": ["los", "angeles", "appliance", "repair"]}
{"url": "http://www.freepressrelease.com.au/ShowFull.asp?date=14397", "timestamp": 1258433050, "tags": ["synverse", "sap", "tibco", "implementation", "services"]}
{"url": "http://blog.fenon.com.br/artigos/dicas-de-como-engravidar-de-uma-menina/", "timestamp": 1258450973, "tags": ["engravidar", "menina", "dicas", "duvidas"]}
{"url": "http://www.synverse.com/index.php?page=consulting", "timestamp": 1258433068, "tags": ["consulting", "services", "proposition", "solution", "business", "strategy", "strategic", "bss", "oss", "network", "assurance", "fsa", "pci", "compliance", "migration"]}
{"url": "http://www.heartmathstore.com/", "timestamp": 1258440117, "tags": ["anxiety", "relief", "biofeedback", "therapy", "stress", "reliever", "health"]}
{"url": "http://www.adultxdating.co.nz/blogs/right-online-dating-service-for-singles/", "timestamp": 1258432278, "tags": ["dating", "website", "singles", "personals", "date", "sites", "relationship", "free", "online", "internet"]}
{"url": "http://www.schd-services.com/iqsysnamedbestcitrixdistributor2009.html", "timestamp": 1258453680, "tags": ["citrix", "distribution"]}
{"url": "http://www.synverse.com/index.php?page=innovation", "timestamp": 1258433066, "tags": ["innovation", "microsoft", "surface"]}
{"url": "http://www.gateway2morocco.com/tours_discover_morocco.html", "timestamp": 1258501282, "tags": ["travel", "packages", "package", "morocco."]}
{"url": "http://blogs.synverse.com/synapse/home/", "timestamp": 1258433058, "tags": ["season7", "wordpress", "theme", "sold"]}
{"url": "http://www.techprspider.com/Synverse-Expanding-India-Operations-feed26915.aspx", "timestamp": 1258433041, "tags": ["tibco", "alfresco", "chordiant", "inted", "joomla", "microsoft", ".net", "oracle", "amdocs", "convergys"]}
{"url": "http://www.indiaabundance.com/shopping/c1_0/Ayurvedic_&_Herbal.html", "timestamp": 1258438016, "tags": ["dabur", "products", "online", "shop", "hair", "care", "oil"]}
{"url": "http://www.synverse.com/", "timestamp": 1258432662, "tags": ["migration", "benefits", "vendors", "application", "examples", "moving", "microsoft", "solution", "offering", "applications"]}
{"url": "http://www.pressreleasepoint.com/synverse-and-gateway-technolabs-partner-provide-end2end-implementation-and-managed-services", "timestamp": 1258433039, "tags": ["cloud", "computing", "innovation", "frameworks", "accelerators", "methodologies", "solutions."]}
{"url": "http://www.bullyvardtattoo.com/The%20joker%20tattoo%20art%20sleeves", "timestamp": 1258430444, "tags": ["motorcycle", "gear", "sports", "accessories", "riding", "tattoo", "sleeves"]}
{"url": "http://cibol.net/", "timestamp": 1258501304, "tags": ["offshore", "outsourcing", "seo", "e-commerce"]}
{"url": "http://www.1888pressrelease.com/synverse-expanding-its-sap-footprint-pr-119052.html", "timestamp": 1258433050, "tags": ["components", "rollout"]}
{"url": "http://www.essaycapital.com/blog/all-about-essay/abesy/896", "timestamp": 1258433489, "tags": ["writing", "assignments", "professional", "help"]}
{"url": "http://www.onlineprnews.com/news/9063-1256037937-synverse-global-expertise-in-deployment-support-services-for-wimax-highlighted-at-itu-telecom-world-in-geneva.html", "timestamp": 1258433033, "tags": ["saas", "integration", "solutions", "european", "telco", "enterprise", "suppliers", "design", "europe", "strategy", "business", "intelligence", "exchange", "online", "platform", "subscription", "payments", "uk", "review", "model", "development", "hosting", "crm", "web", "security", "implementation"]}
{"url": "http://allindiagifts.com/shop/category/Gift_Certificates/", "timestamp": 1258421230, "tags": ["gift", "certificates", "india", "vouchers", "gifts", "online", "westside", "dominos", "pizza", "crossword", "shoppers", "stop", "food", "chocolate", "india."]}
{"url": "http://blog.fenon.com.br/artigos/click-rbs-site-de-noticias/", "timestamp": 1258434675, "tags": ["rbs"]}
{"url": "http://www.boobelly.com/info/7291.html", "timestamp": 1258433051, "tags": ["direcotry", "list", "site", "free", "directoy", "add", "website", "search", "engine", "optimised", "dir", "link", "directory"]}
{"url": "http://www.bigrigattorneys.com/", "timestamp": 1258443235, "tags": ["truck", "accidents", "accident", "crash", "sacramento", "lawyer", "trucks"]}
{"url": "http://countertops-marble-countertops.blogspot.com/", "timestamp": 1258501796, "tags": ["marble", "countertops"]}
{"url": "http://www.checkcity.com/", "timestamp": 1258479196, "tags": ["payday", "loans"]}
{"url": "http://www.essaycapital.com/blog/all-about-essay/philosophy-essays/920", "timestamp": 1258433715, "tags": ["writing", "essay", "philosophy", "research", "papers", "help"]}
{"url": "http://watchcapitalismalovestorymovie.weebly.com/", "timestamp": 1258450655, "tags": ["download", "capitalism", "love", "story"]}
{"url": "http://www.vietnamadvisor.com/", "timestamp": 1258424384, "tags": ["vietnam", "tour", "tours", "hotel", "travel"]}
{"url": "http://webdirectorie.com/computers-and-internet/software/", "timestamp": 1258433052, "tags": ["software", "sap", "global", "enterprise", "integration", "collaboration"]}
{"url": "http://tibcos.wordpress.com/", "timestamp": 1258433057, "tags": ["crm", "eai", "testing", "quality", "assurance", "erp", "business", "solutions", "enterprise"]}
{"url": "http://lifeinsurance-law.com/", "timestamp": 1258456498, "tags": ["life", "insurance", "lawyer", "los", "angeles"]}
{"url": "http://www.synverse.com/index.php?page=synverse-monitoring-framework", "timestamp": 1258433051, "tags": ["quality", "monitoring", "framework", "customer", "needs"]}
{"url": "http://downloadthevampiresassistantonli.weebly.com/", "timestamp": 1258450540, "tags": ["download", "assistant"]}
